{
    "$schema" : "http://json-schema.org/draft-04/schema",
    "id" : "i3dm.featureTable.schema.json",
    "title" : "Instanced 3D Model Feature Table",
    "type" : "object",
    "description" : "A set of Instanced 3D Model semantics that contains values defining the position and appearance properties for instanced models in a tile.",
    "allOf" : [{
        "$ref" : "featureTable.schema.json"
    }, {
        "properties" : {
            "POSITION" : {
                "$ref" : "featureTable.schema.json#/definitions/binaryBodyReference"
            },
            "POSITION_QUANTIZED" : {
                "$ref" : "featureTable.schema.json#/definitions/binaryBodyReference"
            },
            "NORMAL_UP" : {
                "$ref" : "featureTable.schema.json#/definitions/binaryBodyReference"
            },
            "NORMAL_RIGHT" : {
                "$ref" : "featureTable.schema.json#/definitions/binaryBodyReference"
            },
            "NORMAL_UP_OCT32P" : {
                "$ref" : "featureTable.schema.json#/definitions/binaryBodyReference"
            },
            "NORMAL_RIGHT_OCT32P" : {
                "$ref" : "featureTable.schema.json#/definitions/binaryBodyReference"
            },
            "SCALE" : {
                "$ref" : "featureTable.schema.json#/definitions/binaryBodyReference"
            },
            "SCALE_NON_UNIFORM" : {
                "$ref" : "featureTable.schema.json#/definitions/binaryBodyReference"
            },
            "BATCH_ID" : {
                "$ref" : "featureTable.schema.json#/definitions/binaryBodyReference"
            },
            "INSTANCES_LENGTH" : {
                "$ref" : "featureTable.schema.json#/definitions/globalPropertyScalar"
            },
            "QUANTIZED_VOLUME_OFFSET" : {
                "$ref" : "featureTable.schema.json#/definitions/globalPropertyCartesian3"
            },
            "QUANTIZED_VOLUME_SCALE": {
                "$ref" : "featureTable.schema.json#/definitions/globalPropertyCartesian3"
            }
        },
        "anyOf" : [{
          "required" : ["POSITION"]
        }, {
          "required" : ["POSITION_QUANTIZED"]
        }],
        "dependencies" : {
            "POSITION_QUANTIZED" : [
                "QUANTIZED_VOLUME_OFFSET",
                "QUANTIZED_VOLUME_SCALE"
            ],
            "NORMAL_UP" : ["NORMAL_RIGHT"],
            "NORMAL_RIGHT" : ["NORMAL_UP"],
            "NORMAL_UP_OCT32P" : ["NORMAL_RIGHT_OCT32P"],
            "NORMAL_RIGHT_OCT32P" : ["NORMAL_UP_OCT32P"]
        },
        "required" : ["INSTANCES_LENGTH"],
        "additionalProperties" : false
    }]
}
